dbviews/__init__.py
dbviews/apps.py
dbviews/autodetector.py
dbviews/exceptions.py
dbviews/migrations/__init__.py
dbviews/operations.py
dbviews/views/__init__.py
dbviews/views/base.py
dbviews/views/fields.py
dbviews/views/metaclasses.py
dbviews_django-0.1.3.dist-info/LICENSE.txt
dbviews_django-0.1.3.dist-info/METADATA
dbviews_django-0.1.3.dist-info/WHEEL
dbviews_django-0.1.3.dist-info/RECORD
