Metadata-Version: 2.1
Name: dbviews-django
Version: 0.1.3
Summary: Support of database views and materialized views in django web framework.
Home-page: https://github.com/keshavmohta09/dbviews-django/
License: MIT
Author: Keshav Mohta
Author-email: keshavmohta09@gmail.com
Maintainer: Keshav Mohta
Maintainer-email: keshavmohta09@gmail.com
Requires-Python: >=3.9
Classifier: Environment :: Web Environment
Classifier: Framework :: Django
Classifier: Intended Audience :: Developers
Classifier: License :: OSI Approved :: MIT License
Classifier: Operating System :: OS Independent
Classifier: Programming Language :: Python
Classifier: Programming Language :: Python :: 3
Classifier: Programming Language :: Python :: 3.9
Classifier: Programming Language :: Python :: 3.10
Classifier: Programming Language :: Python :: 3.11
Requires-Dist: django (>=4)
